multilang/__init__.py
multilang/translator.py
teko_multi_lang-1.0.2.dist-info/LICENSE.txt
teko_multi_lang-1.0.2.dist-info/METADATA
teko_multi_lang-1.0.2.dist-info/WHEEL
teko_multi_lang-1.0.2.dist-info/top_level.txt
teko_multi_lang-1.0.2.dist-info/RECORD
