Metadata-Version: 2.1
Name: teko-multi-lang
Version: 1.0.2
Summary: Teko translator tool
Home-page: https://git.teko.vn/common-utilities/sample/language-package
Download-URL: https://pypi.org/project/teko-multi-lang/
Author: Thanh Nguyen
Author-email: danthanh92@gmail.com
License: MIT
Keywords: Teko,Teko Translator tools
License-File: LICENSE.txt
Requires-Dist: requests
Requires-Dist: cachetools
